{
  "project_info": {
    "project_number": "659279092122",
    "project_id": "vigilplus-1aba8",
    "storage_bucket": "vigilplus-1aba8.firebasestorage.app"
  },
  "client": [
    {
      "client_info": {
        "mobilesdk_app_id": "1:659279092122:android:94b63192d56ad6edc70223",
        "android_client_info": {
          "package_name": "com.vigilstudios.vigilplus"
        }
      },
      "oauth_client": [],
      "api_key": [
        {
          "current_key": "AIzaSyCdBdQ_aTUd-iO_9mLSCwnAPg9ofeNiqqs"
        }
      ],
      "services": {
        "appinvite_service": {
          "other_platform_oauth_client": []
        }
      }
    }
  ],
  "configuration_version": "1"
}